Metadata-Version: 1.0
Name: PopPyControl
Version: 1.3.3
Summary: Command Poppy Humanoid with python
Home-page: https://github.com/Allanzinh0/PopPyControl
Author: Allanzinh0
Author-email: allanms12@gmail.com
License: MIT
Platform: UNKNOWN
